hca/__init__.py
hca/api_spec.json
hca/constants.py
hca/define_api.py
hca/full_download.py
hca/full_upload.py
hca/parser.py
hca/upload_to_cloud.py
hca/packages/__init__.py
hca/packages/checksumming_io/__init__.py
hca/packages/checksumming_io/checksumming_buffered_reader.py
hca/packages/checksumming_io/checksumming_sink.py
hca/packages/checksumming_io/s3_etag.py
hca_cli-0.1.0.data/scripts/demo.sh
hca_cli-0.1.0.data/scripts/hca
hca_cli-0.1.0.dist-info/DESCRIPTION.rst
hca_cli-0.1.0.dist-info/METADATA
hca_cli-0.1.0.dist-info/RECORD
hca_cli-0.1.0.dist-info/WHEEL
hca_cli-0.1.0.dist-info/metadata.json
hca_cli-0.1.0.dist-info/top_level.txt
