Metadata-Version: 2.0
Name: hca-cli
Version: 0.1.0
Summary: Human Cell Atlas Data Storage System Command Line Interface
Home-page: https://github.com/HumanCellAtlas/data-store-cli
Author: Human Cell Atlas contributors
Author-email: akislyuk@chanzuckerberg.com
License: Apache Software License
Platform: MacOS X
Platform: Posix
Classifier: Intended Audience :: Developers
Classifier: License :: OSI Approved :: Apache Software License
Classifier: Operating System :: MacOS :: MacOS X
Classifier: Operating System :: POSIX
Classifier: Programming Language :: Python
Classifier: Programming Language :: Python :: 2.7
Classifier: Programming Language :: Python :: 3.3
Classifier: Programming Language :: Python :: 3.4
Classifier: Programming Language :: Python :: 3.5
Classifier: Topic :: Software Development :: Libraries :: Python Modules
Requires-Dist: boto3 (==1.4.4)
Requires-Dist: crcmod (==1.7)
Requires-Dist: jsonpointer (==1.10)
Requires-Dist: requests (==2.17.3)
Requires-Dist: enum34 (>=1.1.6,<2); python_version == "2.7"
